bmiptools/__init__.py
bmiptools/pipeline.py
bmiptools/run_gui.py
bmiptools/stack.py
bmiptools/core/__init__.py
bmiptools/core/base.py
bmiptools/core/gpu_utils.py
bmiptools/core/ip_utils.py
bmiptools/core/math_utils.py
bmiptools/core/utils.py
bmiptools/gui/__init__.py
bmiptools/gui/bmiptools_gui.py
bmiptools/gui/gui_basic.py
bmiptools/setting/__init__.py
bmiptools/setting/configure.py
bmiptools/setting/installed_plugins.py
bmiptools/setting/files/experimental_setting_metadata_tag_list.txt
bmiptools/setting/files/global_setting.txt
bmiptools/transformation/__init__.py
bmiptools/transformation/base.py
bmiptools/transformation/alignment/__init__.py
bmiptools/transformation/alignment/registrator.py
bmiptools/transformation/basic/__init__.py
bmiptools/transformation/basic/filters.py
bmiptools/transformation/dynamics/__init__.py
bmiptools/transformation/dynamics/equalizer.py
bmiptools/transformation/dynamics/histogram_matcher.py
bmiptools/transformation/dynamics/standardizer.py
bmiptools/transformation/geometric/__init__.py
bmiptools/transformation/geometric/affine.py
bmiptools/transformation/geometric/cropper.py
bmiptools/transformation/geometric/geometric_tools.py
bmiptools/transformation/restoration/__init__.py
bmiptools/transformation/restoration/_restoration_shared.py
bmiptools/transformation/restoration/decharger.py
bmiptools/transformation/restoration/denoiser.py
bmiptools/transformation/restoration/destriper.py
bmiptools/transformation/restoration/flatter.py
bmiptools/visualization/__init__.py
bmiptools/visualization/geometric/__init__.py
bmiptools/visualization/geometric/change_coordinate_system.py
bmiptools/visualization/graphic_tools/__init__.py
bmiptools/visualization/graphic_tools/basic_graphic_tools.py
bmiptools-1.0.1.dist-info/LICENSE.txt
bmiptools-1.0.1.dist-info/METADATA
bmiptools-1.0.1.dist-info/WHEEL
bmiptools-1.0.1.dist-info/top_level.txt
bmiptools-1.0.1.dist-info/RECORD
