Metadata-Version: 2.1
Name: bmiptools
Version: 1.0.1
Summary: BioMaterial Image Processing tools (bmiptools) is a python library of functions for image processing of certain type of biological images (e.g. FIB-SEM, Back-scattering, ecc... ). The library is equipped with a minimal GUI thought for non-expert users.
Home-page: https://gitlab.mpikg.mpg.de/curcuraci/bmiptools
Author: Luca Curcuraci
Author-email: Luca.Curcuraci@mpikg.mpg.de
Project-URL: Bug tracker, https://gitlab.mpikg.mpg.de/curcuraci/bmiptools/-/issues/new
Project-URL: Documentation, https://bmiptools.readthedocs.io/en/latest/
Classifier: Programming Language :: Python :: 3.8
Classifier: License :: OSI Approved :: Apache Software License
Classifier: Operating System :: OS Independent
Classifier: Topic :: Scientific/Engineering :: Image Processing
Classifier: Topic :: Software Development :: Libraries :: Python Modules
Classifier: Topic :: Software Development :: User Interfaces
Classifier: Intended Audience :: Science/Research
Requires-Python: >=3.8
License-File: LICENSE.txt
Requires-Dist: benedict (>=0.3.2)
Requires-Dist: dill (==0.3.4)
Requires-Dist: ExifRead (==2.3.2)
Requires-Dist: imageio (==2.9.0)
Requires-Dist: joblib (==1.0.1)
Requires-Dist: magicgui (==0.2.11)
Requires-Dist: matplotlib (==3.4.2)
Requires-Dist: n2v (==0.3.1)
Requires-Dist: napari (==0.4.11)
Requires-Dist: numpy (==1.18.5)
Requires-Dist: opencv-python (==4.5.3.56)
Requires-Dist: Pillow (==9.1.1)
Requires-Dist: python-benedict (>=0.24.3)
Requires-Dist: PyWavelets (==1.1.1)
Requires-Dist: scikit-image (==0.18.1)
Requires-Dist: scipy (==1.4.1)
Requires-Dist: tqdm (==4.62.1)
Requires-Dist: Keras (==2.3.1)
Requires-Dist: Keras-Applications (==1.0.8)
Requires-Dist: Keras-Preprocessing (==1.1.2)
Requires-Dist: protobuf (==3.17.2)
Requires-Dist: tensorboard (==2.5.0)
Requires-Dist: tensorboard-plugin-wit (==1.6.0.post2)
Requires-Dist: tensorflow (==2.3.0)
Requires-Dist: tensorflow-estimator (<=2.6.0)
Requires-Dist: PyQt5 (==5.12.3)
Requires-Dist: PyQt5-sip (==4.19.18)
Requires-Dist: PyQtChart (==5.12)
Requires-Dist: PyQtWebEngine (==5.12.1)
